vapi/__init__.py
vapi/analytics/__init__.py
vapi/analytics/client.py
vapi/analytics/raw_client.py
vapi/assistants/__init__.py
vapi/assistants/client.py
vapi/assistants/raw_client.py
vapi/assistants/types/__init__.py
vapi/assistants/types/update_assistant_dto_background_sound.py
vapi/assistants/types/update_assistant_dto_background_sound_zero.py
vapi/assistants/types/update_assistant_dto_client_messages_item.py
vapi/assistants/types/update_assistant_dto_credentials_item.py
vapi/assistants/types/update_assistant_dto_first_message_mode.py
vapi/assistants/types/update_assistant_dto_hooks_item.py
vapi/assistants/types/update_assistant_dto_model.py
vapi/assistants/types/update_assistant_dto_server_messages_item.py
vapi/assistants/types/update_assistant_dto_transcriber.py
vapi/assistants/types/update_assistant_dto_voice.py
vapi/assistants/types/update_assistant_dto_voicemail_detection.py
vapi/assistants/types/update_assistant_dto_voicemail_detection_zero.py
vapi/calls/__init__.py
vapi/calls/client.py
vapi/calls/raw_client.py
vapi/calls/types/__init__.py
vapi/calls/types/call_controller_find_all_paginated_request_sort_order.py
vapi/calls/types/create_calls_response.py
vapi/campaigns/__init__.py
vapi/campaigns/client.py
vapi/campaigns/raw_client.py
vapi/campaigns/types/__init__.py
vapi/campaigns/types/campaign_controller_find_all_request_sort_order.py
vapi/campaigns/types/campaign_controller_find_all_request_status.py
vapi/campaigns/types/update_campaign_dto_status.py
vapi/chats/__init__.py
vapi/chats/client.py
vapi/chats/raw_client.py
vapi/chats/types/__init__.py
vapi/chats/types/create_chat_dto_input.py
vapi/chats/types/create_chat_dto_input_one_item.py
vapi/chats/types/create_chats_response.py
vapi/chats/types/create_response_chats_response.py
vapi/chats/types/list_chats_request_sort_order.py
vapi/chats/types/open_ai_responses_request_input.py
vapi/chats/types/open_ai_responses_request_input_one_item.py
vapi/client.py
vapi/core/__init__.py
vapi/core/api_error.py
vapi_server_sdk-1.8.0.dist-info/METADATA
vapi_server_sdk-1.8.0.dist-info/WHEEL
vapi_server_sdk-1.8.0.dist-info/RECORD
